{
  "$schema": "https://developer.microsoft.com/json-schemas/fabric/item/report/definition/visualContainer/2.7.0/schema.json",
  "name": "ca55036021532ba65c93",
  "position": {
    "x": 1228.8997078870495,
    "y": 46.114897760467379,
    "z": 20001,
    "height": 35,
    "width": 35
  },
  "visual": {
    "visualType": "actionButton",
    "objects": {
      "icon": [
        {
          "properties": {
            "shapeType": {
              "expr": {
                "Literal": {
                  "Value": "'reset'"
                }
              }
            }
          },
          "selector": {
            "id": "default"
          }
        }
      ],
      "fill": [
        {
          "properties": {
            "fillColor": {
              "solid": {
                "color": {
                  "expr": {
                    "ThemeDataColor": {
                      "ColorId": 9,
                      "Percent": 0
                    }
                  }
                }
              }
            }
          },
          "selector": {
            "id": "default"
          }
        },
        {
          "properties": {
            "fillColor": {
              "solid": {
                "color": {
                  "expr": {
                    "Literal": {
                      "Value": "'#CC0000'"
                    }
                  }
                }
              }
            }
          },
          "selector": {
            "id": "hover"
          }
        }
      ],
      "shape": [
        {
          "properties": {
            "tileShape": {
              "expr": {
                "Literal": {
                  "Value": "'oval'"
                }
              }
            }
          },
          "selector": {
            "id": "default"
          }
        }
      ]
    },
    "drillFilterOtherVisuals": true
  },
  "howCreated": "InsertVisualButton"
}